ctxlog/__init__.py
ctxlog/config.py
ctxlog/handlers.py
ctxlog/level.py
ctxlog/log.py
ctxlog/logger.py
ctxlog-1.0.0.dist-info/LICENSE
ctxlog-1.0.0.dist-info/METADATA
ctxlog-1.0.0.dist-info/WHEEL
ctxlog-1.0.0.dist-info/RECORD
