Metadata-Version: 2.3
Name: ctxlog
Version: 1.0.0
Summary: Structured logging library for Python
Keywords: logging,structured-logging,json-logging,context-logging
Requires-Python: >=3.9,<4.0
Classifier: Development Status :: 4 - Beta
Classifier: Intended Audience :: Developers
Classifier: License :: OSI Approved :: MIT License
Classifier: Programming Language :: Python :: 3
Classifier: Programming Language :: Python :: 3.9
Classifier: Programming Language :: Python :: 3.10
Classifier: Programming Language :: Python :: 3.11
Classifier: Programming Language :: Python :: 3.12
Classifier: Programming Language :: Python :: 3.13
Classifier: Topic :: System :: Logging
Provides-Extra: dev
Provides-Extra: docs
Requires-Dist: furo (>=2024.8.6,<2025.0.0) ; extra == "docs"
Requires-Dist: mypy (>=1.15.0,<2.0.0) ; extra == "dev"
Requires-Dist: myst-parser (>=3.0.0,<4.0.0) ; extra == "docs"
Requires-Dist: pytest (>=8.3.5,<9.0.0) ; extra == "dev"
Requires-Dist: pytest-cov (>=4.1.0,<5.0.0) ; extra == "dev"
Requires-Dist: ruff (>=0.11.9,<0.12.0) ; extra == "dev"
Requires-Dist: sphinx (>=7.4.7,<8.0.0) ; extra == "docs"
Requires-Dist: sphinx-autodoc-typehints (>=2.3.0,<3.0.0) ; extra == "docs"
